aetherllm/Aether.py
aetherllm/AetherAPI.py
aetherllm/AetherCall.py
aetherllm/AetherFunction.py
aetherllm/__init__.py
aetherllm-0.1.9.dist-info/METADATA
aetherllm-0.1.9.dist-info/WHEEL
aetherllm-0.1.9.dist-info/top_level.txt
aetherllm-0.1.9.dist-info/RECORD
