Metadata-Version: 2.1
Name: aetherllm
Version: 0.1.9
Summary: A Python library for CI/CD with LLMs.
Author: Wadih Pazos
Author-email: wadpod7@gmail.com
Requires-Dist: openai
Requires-Dist: jsonschema
Requires-Dist: pydantic
Requires-Dist: requests
Requires-Dist: aiohttp
Requires-Dist: asyncio
